services/__init__.py
atd_knack_services-0.0.3.dist-info/METADATA
atd_knack_services-0.0.3.dist-info/WHEEL
atd_knack_services-0.0.3.dist-info/top_level.txt
atd_knack_services-0.0.3.dist-info/RECORD
