Metadata-Version: 2.1
Name: atd-knack-services
Version: 0.0.3
Summary: Integration services for ATD's knack applications.
Home-page: http://github.com/cityofaustin/atd-knack-services
Author: John Clary
Author-email: john.clary@austintexas.gov
License: Public Domain
Keywords: knack api integration python
Platform: UNKNOWN
Classifier: Development Status :: 4 - Beta
Classifier: Intended Audience :: Developers
Classifier: License :: Public Domain
Classifier: Programming Language :: Python :: 3
Requires-Dist: arrow
Requires-Dist: boto3
Requires-Dist: knackpy
Requires-Dist: sodapy
